prefix/__init__.py
prefix/_/__init__.py
prefix/_/action_tree.py
prefix/_/build_log.py
prefix/_/command.py
prefixcommand/__init__.py
prefixcommand-0.0.2.dist-info/LICENSE
prefixcommand-0.0.2.dist-info/METADATA
prefixcommand-0.0.2.dist-info/WHEEL
prefixcommand-0.0.2.dist-info/top_level.txt
prefixcommand-0.0.2.dist-info/zip-safe
prefixcommand-0.0.2.dist-info/RECORD
