Metadata-Version: 2.1
Name: prefixcommand
Version: 0.0.2
Summary: Run commands in 'environments', with a focus on prefix commands
Home-page: https://gitlab.com/jjlee1/prefix
Platform: any
License-File: LICENSE
